endoflifedate/__init__.py
endoflifedate/api_client.py
endoflifedate/api_response.py
endoflifedate/configuration.py
endoflifedate/exceptions.py
endoflifedate/py.typed
endoflifedate/rest.py
endoflifedate/api/__init__.py
endoflifedate/api/default_api.py
endoflifedate/models/__init__.py
endoflifedate/models/cycle.py
endoflifedate/models/cycle_cycle.py
endoflifedate/models/cycle_discontinued.py
endoflifedate/models/cycle_eol.py
endoflifedate/models/cycle_lts.py
endoflifedate/models/cycle_support.py
endoflifedate-1.0.0.dist-info/METADATA
endoflifedate-1.0.0.dist-info/WHEEL
endoflifedate-1.0.0.dist-info/top_level.txt
endoflifedate-1.0.0.dist-info/RECORD
