Metadata-Version: 2.1
Name: endoflifedate
Version: 1.0.0
Summary: endoflife.date
Home-page: https://github.com/oapicf/endoflife.date-api-clients
Author: OpenAPI Clients Factory
Author-email: blah+oapicf@cliffano.com
License: MIT
Keywords: OpenAPI,OpenAPI-Generator,endoflife.date
Platform: UNKNOWN
Requires-Dist: pydantic (>=2)
Requires-Dist: python-dateutil
Requires-Dist: typing-extensions (>=4.7.1)
Requires-Dist: urllib3 (<2.1.0,>=1.25.3)
